README.md
setup.py
VerbalExpressions.egg-info/PKG-INFO
VerbalExpressions.egg-info/SOURCES.txt
VerbalExpressions.egg-info/dependency_links.txt
VerbalExpressions.egg-info/top_level.txt
VerbalExpressions.egg-info/zip-safe
verbalexpressions/__init__.py
verbalexpressions/verbal_expressions.py