Metadata-Version: 1.1
Name: VerbalExpressions
Version: 0.0.2
Summary: Make difficult regular expressions easy! Python port of the awesome VerbalExpressions repo - https://github.com/jehna/VerbalExpressions
Home-page: https://github.com/VerbalExpressions/PythonVerbalExpressions
Author: Victor Titor, Yan Wenjun, diogobeda, Mihai Ionut Vilcu, Peder Soholt, Sameer Raghuram, Kharms
Author-email: UNKNOWN
License: MIT
Platform: UNKNOWN
Classifier: License :: OSI Approved :: MIT License
Classifier: Programming Language :: Python
Classifier: Programming Language :: Python :: 2.7
Classifier: Programming Language :: Python :: 3.2
Classifier: Programming Language :: Python :: 3.3
Classifier: Programming Language :: Python :: 3.4
Classifier: Programming Language :: Python :: 3.5
Classifier: Programming Language :: Python :: 3.6
Classifier: Topic :: Software Development :: Libraries
Classifier: Topic :: Text Processing
